nonebot_adapter_gocq/__init__.py
nonebot_adapter_gocq/bot.py
nonebot_adapter_gocq/bot.pyi
nonebot_adapter_gocq/config.py
nonebot_adapter_gocq/event.py
nonebot_adapter_gocq/exception.py
nonebot_adapter_gocq/message.py
nonebot_adapter_gocq/permission.py
nonebot_adapter_gocq/utils.py
nonebot_adapter_gocq-0.1.2.dist-info/LICENSE
nonebot_adapter_gocq-0.1.2.dist-info/WHEEL
nonebot_adapter_gocq-0.1.2.dist-info/METADATA
nonebot_adapter_gocq-0.1.2.dist-info/RECORD
