Metadata-Version: 2.1
Name: nonebot-adapter-gocq
Version: 0.1.2
Summary: go-cqhttp adapter for nonebot2
Home-page: https://github.com/Jigsaw111/nonebot-adapter-gocq
License: MIT
Keywords: bot,qq,qqbot,coolq,cqhttp,go-cqhttp
Author: Jigsaw
Author-email: j1g5aw@foxmail.com
Requires-Python: >=3.7.3,<4.0.0
Classifier: Development Status :: 5 - Production/Stable
Classifier: Framework :: Robot Framework
Classifier: Framework :: Robot Framework :: Library
Classifier: License :: OSI Approved :: MIT License
Classifier: Operating System :: OS Independent
Classifier: Programming Language :: Python :: 3
Classifier: Programming Language :: Python :: 3.8
Classifier: Programming Language :: Python :: 3.9
Requires-Dist: httpx (>=0.17.0,<0.18.0)
Requires-Dist: nonebot2 (==2.0.0-alpha.13)
Project-URL: Documentation, https://v2.nonebot.dev/
Project-URL: Repository, https://github.com/Jigsaw111/nonebot-adapter-gocq
